indiansearchengine/__init__.py
IndianSearchengineSurya-0.2.dist-info/METADATA
IndianSearchengineSurya-0.2.dist-info/WHEEL
IndianSearchengineSurya-0.2.dist-info/top_level.txt
IndianSearchengineSurya-0.2.dist-info/RECORD
